odoo/addons/shopinvader_api_cart_options/README.rst
odoo/addons/shopinvader_api_cart_options/__init__.py
odoo/addons/shopinvader_api_cart_options/__manifest__.py
odoo/addons/shopinvader_api_cart_options/helper.py
odoo/addons/shopinvader_api_cart_options/schemas.py
odoo/addons/shopinvader_api_cart_options/test.py
odoo/addons/shopinvader_api_cart_options/i18n/shopinvader_api_cart_options.pot
odoo/addons/shopinvader_api_cart_options/readme/CONTRIBUTORS.md
odoo/addons/shopinvader_api_cart_options/readme/DESCRIPTION.md
odoo/addons/shopinvader_api_cart_options/readme/USAGE.md
odoo/addons/shopinvader_api_cart_options/static/description/index.html
odoo/addons/shopinvader_api_cart_options/tests/__init__.py
odoo/addons/shopinvader_api_cart_options/tests/models.py
odoo/addons/shopinvader_api_cart_options/tests/schemas.py
odoo/addons/shopinvader_api_cart_options/tests/test_shopinvader_api_cart_options.py
odoo_addon_shopinvader_api_cart_options-16.0.1.0.2.dist-info/METADATA
odoo_addon_shopinvader_api_cart_options-16.0.1.0.2.dist-info/WHEEL
odoo_addon_shopinvader_api_cart_options-16.0.1.0.2.dist-info/top_level.txt
odoo_addon_shopinvader_api_cart_options-16.0.1.0.2.dist-info/RECORD
